naptan/__init__.py
naptan/atco_codes.csv
naptan/naptan.py
naptan-0.2.1.dist-info/METADATA
naptan-0.2.1.dist-info/WHEEL
naptan-0.2.1.dist-info/licenses/LICENSE.txt
naptan-0.2.1.dist-info/RECORD
