Metadata-Version: 2.1
Name: naptan
Version: 0.2.1
Summary: Python package to quickly and easily get public transport access node data from the UK's NaPTAN API.
Project-URL: homepage, https://mullinscr.github.io/naptan/
Project-URL: documentation, https://mullinscr.github.io/naptan/
Project-URL: repository, https://github.com/mullinscr/naptan
Author-email: Callum Mullins <mullinscr@gmail.com>
License: MIT
License-File: LICENSE.txt
Keywords: ATCO,Bus,DfT,NPTG,NaPTAN,Public Transport,Stop,Transport,Traveline
Classifier: Programming Language :: Python :: 3
Requires-Python: >=3
Requires-Dist: folium>=0.9.0
Requires-Dist: pandas
Requires-Dist: pyproj>=2.0.0
Requires-Dist: requests
Requires-Dist: typing; python_version < '3.5'
Provides-Extra: dev
Requires-Dist: importlib-resources; extra == 'dev'
Requires-Dist: pytest; extra == 'dev'
